skyer_llm/__init__.py
skyer_llm/data.py
skyer_llm/inference.py
skyer_llm/model.py
skyer_llm/preprocess.py
skyer_llm/pretrain.py
skyer_llm/transformer.py
skyer_llm-0.1.2.dist-info/LICENSE
skyer_llm-0.1.2.dist-info/METADATA
skyer_llm-0.1.2.dist-info/WHEEL
skyer_llm-0.1.2.dist-info/top_level.txt
skyer_llm-0.1.2.dist-info/RECORD
